LICENSE
MANIFEST.in
README.md
helga_spongebob.py
setup.py
helga_spongebob.egg-info/PKG-INFO
helga_spongebob.egg-info/SOURCES.txt
helga_spongebob.egg-info/dependency_links.txt
helga_spongebob.egg-info/entry_points.txt
helga_spongebob.egg-info/top_level.txt