Metadata-Version: 1.1
Name: helga-spongebob
Version: 0.1
Summary: HeLgA PlUgIn tO Do mOcKiNg sPoNgEbOb tExT
Home-page: https://github.com/shaunduncan/helga-spongebob
Author: Shaun Duncan
Author-email: shaun.duncan@gmail.com
License: MIT
Keywords: helga spongebob
Platform: UNKNOWN
Classifier: Development Status :: 4 - Beta
Classifier: Topic :: Communications :: Chat :: Internet Relay Chat
Classifier: Framework :: Twisted
Classifier: License :: OSI Approved :: MIT License
Classifier: Operating System :: OS Independent
Classifier: Programming Language :: Python
Classifier: Programming Language :: Python :: 2
Classifier: Programming Language :: Python :: 2.6
Classifier: Programming Language :: Python :: 2.7
Classifier: Topic :: Software Development :: Libraries :: Python Modules
